followmee_py/__init__.py
followmee_py/exceptions.py
followmee_py/followmee_api.py
followmee_py/models.py
followmee_py/rest_adapter.py
followmee_py-2024.11.1.0.dist-info/METADATA
followmee_py-2024.11.1.0.dist-info/WHEEL
followmee_py-2024.11.1.0.dist-info/licenses/LICENSE
followmee_py-2024.11.1.0.dist-info/RECORD
